<?xml version="1.0" encoding="UTF-8"?>
<!DOCTYPE beans PUBLIC "-//SPRING//DTD BEAN//EN" "http://www.springframework.org/dtd/spring-beans.dtd">

<beans>


    <!-- DRT : Discuss and Review Tool -->
    
    <bean id="drtDAO" class="org.pgist.sarp.drt.DRTDAOImpl">
        <property name="sessionFactory">
            <ref bean="sessionFactory" />
        </property>
    </bean>


    <bean id="drtService" parent="baseTransactionProxy">
        <property name="target">
            <bean class="org.pgist.sarp.drt.DRTServiceImpl">
                <property name="drtDAO" ref="drtDAO"/>
                <property name="systemDAO" ref="systemDAO"/>
            </bean>
        </property>
    </bean>


    <bean id="drtAgent" class="org.pgist.sarp.drt.DRTAgent">
        <property name="drtService" ref="drtService"/>
        <property name="systemService" ref="systemService"/>
        <property name="searchHelper" ref="searchHelper"/>
    </bean>


    <!-- BCT : Brainstorming Concerns Tool -->
    
    <bean id="bctDAO" class="org.pgist.sarp.bct.BCTDAOImpl">
        <property name="sessionFactory">
            <ref bean="sessionFactory" />
        </property>
    </bean>


    <bean id="bctService" parent="baseTransactionProxy">
        <property name="target">
            <bean class="org.pgist.sarp.bct.BCTServiceImpl">
                <property name="userDAO" ref="userDAO"/>
                <property name="bctDAO" ref="bctDAO"/>
                <property name="tagDAO" ref="tagDAO"/>
                <property name="analyzer" ref="tagAnalyzer"/>
                <property name="systemDAO" ref="systemDAO"/>
            </bean>
        </property>
    </bean>


    <bean id="bctAgent" class="org.pgist.sarp.bct.BCTAgent">
        <property name="bctService" ref="bctService"/>
        <property name="userDAO" ref="userDAO"/>
        <property name="systemService" ref="systemService"/>
        <property name="searchHelper" ref="searchHelper"/>
    </bean>


    <!-- CST : Concern Synthesis Tool -->
    
    <bean id="cstDAO" class="org.pgist.sarp.cst.CSTDAOImpl">
        <property name="sessionFactory">
            <ref bean="sessionFactory" />
        </property>
    </bean>


    <bean id="cstService" parent="baseTransactionProxy">
        <property name="target">
            <bean class="org.pgist.sarp.cst.CSTServiceImpl">
                <property name="bctDAO" ref="bctDAO"/>
                <property name="cstDAO" ref="cstDAO"/>
                <property name="tagDAO" ref="tagDAO"/>
            </bean>
        </property>
    </bean>


    <bean id="cstAgent" class="org.pgist.sarp.cst.CSTAgent">
        <property name="bctService" ref="bctService"/>
        <property name="cstService" ref="cstService"/>
    </bean>

    <!-- CHT : Concern Hierarchy Tool -->
    
    <!-- VTT : Value Tree Tool -->
    

</beans>

